{
  "title": "Home",
  "content": "intro.md",
  "gallery": [{
    "title": "Design Systems",
    "imageInActive": "../images/gallery/design-systems_inactive@2x.png",
    "imageActive": "../images/gallery/design-systems_active@2x.png"
  },
  {
    "title": "The Path to Yes",
    "imageInActive": "../images/gallery/path-to-yes_inactive@2x.png",
    "imageActive": "../images/gallery/path-to-yes_active@2x.png"
  },
  {
    "title": "Coming Soon",
    "imageInActive": "../images/gallery/coming-soon@2x.png",
    "imageActive": "../images/gallery/coming-soon@2x.png"
  },
  {
    "title": "Coming Soon",
    "imageInActive": "../images/gallery/coming-soon@2x.png",
    "imageActive": "../images/gallery/coming-soon@2x.png"
  },
  {
    "title": "Coming Soon",
    "imageInActive": "../images/gallery/coming-soon@2x.png",
    "imageActive": "../images/gallery/coming-soon@2x.png"
  }
]
}
